Workbook

Sheet Read Me
A1: HUL DCF Valuation Model
A3: Purpose: Standalone DCF for Hindustan Unilever Ltd (HINDUNILVR), built for CV/internship project use.
A4: Tabs:
A5: 1. Historicals - 3-yr actuals (FY24-FY26), sourced from Screener.in
A6: 2. Assumptions - WACC build, growth, margin, tax, capex/D&A, working capital
A7: 3. FCFF Build - 5-year explicit forecast (FY27E-FY31E)
A8: 4. DCF Valuation - PV of FCFF + terminal value, bridge to equity value/share
A9: 5. Sensitivity - WACC x terminal growth grid on value/share
A10: 6. Comps Cross-Check - EV/EBITDA & P/E vs FMCG peers, implied share price sanity check
A12: Known data caveats (read before using in an interview):
A13: - FY26 Net Profit/PBT is inflated by a one-off Other Income spike (~Rs 4,923 Cr,
A14: concentrated in Dec-2025 quarter). DCF uses Operating Profit (EBIT), which excludes
... A34: stability, while peer multiples capture that premium directly.

Sheet Historicals
A1: HUL - Historical Financials (Consolidated, Rs Cr)
A2: Source: Screener.in (screener.in/company/HINDUNILVR/consolidated), pulled 18-Jul-2026
A4: Metric | B4: FY24 (Mar-24) | C4: FY25 (Mar-25) | D4: FY26 (Mar-26)
A5: Sales | B5: 61896 | C5: 61328 | D5: 64468
A6: Operating Profit (EBIT) | B6: 14659 | C6: 14698 | D6: 15039
A7: OPM % | B7: =B6/B5 -> 0.23683275 | C7: =C6/C5 -> 0.23966214 | D7: =D6/D5 -> 0.23327853
A8: Other Income | B8: 817 | C8: 1355 | D8: 4923
A9: Depreciation | B9: 1216 | C9: 1253 | D9: 1333
A10: Interest Expense | B10: 334 | C10: 381 | D10: 410
A11: Profit Before Tax | B11: 13926 | C11: 14419 | D11: 18219
A12: Effective Tax % | B12: =(B11-B13)/B11 -> 0.26166882 | C12: =(C11-C13)/C11 -> 0.25993481 | D12: =(D11-D13)/D11 -> 0.1734453
A13: Net Profit | B13: 10282 | C13: 10671 | D13: 15059
A14: EPS (Rs) | B14: 43.74 | C14: 45.32 | D14: 64.01
A15: Cash from Operations (CFO) | B15: 15469 | C15: 11886 | D15: 10999
A16: Free Cash Flow (as reported) | B16: 14012 | C16: 10624 | D16: 9667
A17: Borrowings | B17: 1484 | C17: 1648 | D17: 1478
A18: Investments (cash-equiv proxy) | B18: 4625 | C18: 3810 | D18: 4359
A19: Equity Capital (Rs Cr) | B19: 235 | C19: 235 | D19: 235

Sheet Assumptions
A1: HUL - DCF Assumptions
A3: WACC Build
A4: Risk-free rate (India 10Y G-Sec) | B4: 0.069 | C4: Source: tradingeconomics.com/macromicro.me, ~6.9-7.1% as of Jul-2026
A5: Equity Risk Premium (India) | B5: 0.07 | C5: Standard market-convention assumption, not a live pull
A6: Beta (5Y monthly) | B6: 0.32 | C6: Yahoo Finance & Investing.com both ~0.27-0.32 (5Y monthly); GuruFocus's 0.80 excluded as methodology outlier
A7: Cost of Equity (Ke) | B7: =B4+B6*B5 -> 0.0914 | C7: Risk-free + Beta x ERP
A8: Pre-tax Cost of Debt (Kd) | B8: 0.075 | C8: Estimate - HUL is near debt-free (BSE/CRISIL rating not directly pulled); minimal WACC impact
A9: Normalized Tax Rate | B9: 0.255 | C9: Normalized (excludes FY26 17% anomaly)
A10: Market Cap (Rs Cr) | B10: 509914 | C10: Source: Screener.in, 18-Jul-2026
A11: Total Debt / Borrowings (Rs Cr) | B11: 1478 | C11: FY26 Borrowings, Source: Screener.in
A12: Weight of Equity | B12: =B10/(B10+B11) -> 0.99710985 | C12: MktCap/(MktCap+Debt)
A13: Weight of Debt | B13: =B11/(B10+B11) -> 0.0028901508 | C13: Debt/(MktCap+Debt)
A14: WACC | B14: =B12*B7+B13*B8*(1-B9) -> 0.091297327 | C14: We*Ke + Wd*Kd*(1-Tax)
A17: Revenue Growth & Operating Assumptions
A18: Revenue Growth - Year 1 (FY27E) | B18: 0.06 | C18: Fades from historical 5Y CAGR (7%) toward terminal rate
A19: Revenue Growth - Year 2 (FY28E) | B19: 0.055
A20: Revenue Growth - Year 3 (FY29E) | B20: 0.05
A21: Revenue Growth - Year 4 (FY30E) | B21: 0.0475
A22: Revenue Growth - Year 5 (FY31E) | B22: 0.045 | C22: Converges near terminal growth
A23: Terminal Growth Rate (g) | B23: 0.0425 | C23: Capped near India long-run nominal GDP growth proxy
A24: EBIT Margin (all fcst years) | B24: 0.235 | C24: In line with 3Y historical range of 23-24% (Screener.in)
A25: D&A % of Sales | B25: 0.02 | C25: FY26 actual: 1,333/64,468 = 2.07%
A26: Capex % of Sales | B26: 0.022 | C26: Slightly above D&A - modest growth capex, asset-light FMCG
A27: Working Capital % of Sales | B27: -0.07 | C27: Approximated from Screener.in 'Working Capital Days' ratio (~-26 days avg FY24-26 / 365)

Sheet FCFF Build
A1: HUL - FCFF Build (Rs Cr)
B3: FY26A (Base) | C3: FY27E | D3: FY28E | E3: FY29E | F3: FY30E | G3: FY31E
A4: Revenue Growth % | C4: =Assumptions!B18 -> 0.06 | D4: =Assumptions!B19 -> 0.055 | E4: =Assumptions!B20 -> 0.05 | F4: =Assumptions!B21 -> 0.0475 | G4: =Assumptions!B22 -> 0.045
A5: Revenue | B5: =Historicals!D5 -> 64468 | C5: =B5*(1+C4) -> 68336.08 | D5: =C5*(1+D4) -> 72094.564 | E5: =D5*(1+E4) -> 75699.293 | F5: =E5*(1+F4) -> 79295.009 | G5: =F5*(1+G4) -> 82863.284
A6: EBIT Margin % | B6: =Historicals!D7 -> 0.23327853 | C6: =Assumptions!$B$24 -> 0.235 | D6: =Assumptions!$B$24 -> 0.235 | E6: =Assumptions!$B$24 -> 0.235 | F6: =Assumptions!$B$24 -> 0.235 | G6: =Assumptions!$B$24 -> 0.235
A7: EBIT | B7: =Historicals!D6 -> 15039 | C7: =C5*C6 -> 16058.979 | D7: =D5*D6 -> 16942.223 | E7: =E5*E6 -> 17789.334 | F7: =F5*F6 -> 18634.327 | G7: =G5*G6 -> 19472.872
A8: Tax Rate % | C8: =Assumptions!$B$9 -> 0.255 | D8: =Assumptions!$B$9 -> 0.255 | E8: =Assumptions!$B$9 -> 0.255 | F8: =Assumptions!$B$9 -> 0.255 | G8: =Assumptions!$B$9 -> 0.255
A9: NOPAT | C9: =C7*(1-C8) -> 11963.939 | D9: =D7*(1-D8) -> 12621.956 | E9: =E7*(1-E8) -> 13253.054 | F9: =F7*(1-F8) -> 13882.574 | G9: =G7*(1-G8) -> 14507.29
A10: (+) D&A | C10: =Assumptions!$B$25*C5 -> 1366.7216 | D10: =Assumptions!$B$25*D5 -> 1441.8913 | E10: =Assumptions!$B$25*E5 -> 1513.9859 | F10: =Assumptions!$B$25*F5 -> 1585.9002 | G10: =Assumptions!$B$25*G5 -> 1657.2657
A11: (-) Capex | C11: =Assumptions!$B$26*C5 -> 1503.3938 | D11: =Assumptions!$B$26*D5 -> 1586.0804 | E11: =Assumptions!$B$26*E5 -> 1665.3844 | F11: =Assumptions!$B$26*F5 -> 1744.4902 | G11: =Assumptions!$B$26*G5 -> 1822.9923
A12: Working Capital (Balance) | B12: =Assumptions!B27*B5 -> -4512.76 | C12: =Assumptions!$B$27*C5 -> -4783.5256 | D12: =Assumptions!$B$27*D5 -> -5046.6195 | E12: =Assumptions!$B$27*E5 -> -5298.9505 | F12: =Assumptions!$B$27*F5 -> -5550.6506 | G12: =Assumptions!$B$27*G5 -> -5800.4299
A13: (-) Increase in WC | C13: =C12-B12 -> -270.7656 | D13: =D12-C12 -> -263.09391 | E13: =E12-D12 -> -252.33098 | F13: =F12-E12 -> -251.70015 | G13: =G12-F12 -> -249.77928
A14: FCFF | C14: =C9+C10-C11-C13 -> 12098.033 | D14: =D9+D10-D11-D13 -> 12740.861 | E14: =E9+E10-E11-E13 -> 13353.986 | F14: =F9+F10-F11-F13 -> 13975.684 | G14: =G9+G10-G11-G13 -> 14591.342

Sheet DCF Valuation
A1: HUL - DCF Valuation (Rs Cr, except per-share)
B3: FY27E | C3: FY28E | D3: FY29E | E3: FY30E | F3: FY31E
A4: FCFF | B4: ='FCFF Build'!C14 -> 12098.033 | C4: ='FCFF Build'!D14 -> 12740.861 | D4: ='FCFF Build'!E14 -> 13353.986 | E4: ='FCFF Build'!F14 -> 13975.684 | F4: ='FCFF Build'!G14 -> 14591.342
A5: Discount Period | B5: 1 | C5: 2 | D5: 3 | E5: 4 | F5: 5
A6: Discount Factor | B6: =1/(1+$B$16)^B5 -> 0.91634056 | C6: =1/(1+$B$16)^C5 -> 0.83968001 | D6: =1/(1+$B$16)^D5 -> 0.76943285 | E6: =1/(1+$B$16)^E5 -> 0.70506253 | F6: =1/(1+$B$16)^F5 -> 0.64607739
A7: PV of FCFF | B7: =B4*B6 -> 11085.918 | C7: =C4*C6 -> 10698.246 | D7: =D4*D6 -> 10274.996 | E7: =E4*E6 -> 9853.731 | F7: =F4*F6 -> 9427.1363
A9: Sum PV of Explicit FCFF (FY27E-FY31E) | B9: =SUM(B7:F7) -> 51340.027
A11: Terminal Value (Year 5)
A12: Terminal Growth Rate (g) | B12: =Assumptions!B23 -> 0.0425
A13: WACC | B13: =Assumptions!B14 -> 0.091297327
A14: Terminal Value = FCFF5*(1+g)/(WACC-g) | B14: =F4*(1+B12)/(B13-B12) -> 311727.61
A15: PV of Terminal Value | B15: =B14*F6 -> 201400.16
A16: WACC (used above) | B16: =Assumptions!B14 -> 0.091297327
A18: Enterprise Value | B18: =B9+B15 -> 252740.19
A19: (-) Total Debt | B19: =-Assumptions!B11 -> -1478
A20: (+) Cash & Investments | B20: =Historicals!D18 -> 4359
A21: Equity Value | B21: =B18+B19+B20 -> 255621.19
A22: Shares Outstanding (Cr) | B22: =Historicals!D19 -> 235
A23: Value per Share (Rs) | B23: =B21/B22 -> 1087.7497
A24: Current Market Price (Rs) | B24: 2170
A25: Upside / (Downside) % | B25: =B23/B24-1 -> -0.49873284

Sheet Sensitivity
A1: HUL - Sensitivity: Value per Share (Rs) vs WACC & Terminal Growth
A2: Rows = WACC, Columns = Terminal Growth Rate (g)
A4: WACC \ g | B4: 0.035 | C4: 0.03875 | D4: 0.0425 | E4: 0.04625 | F4: 0.05
A5: 0.082 | B5: =('FCFF Build'!$C$14/(1+$A5)^1+'FCFF Build'!$D$14/(1+$A5)^2+'FCFF Build'!$E$14/(1+$A5)^3+'FCFF Build'!$F$14/(1+$A5)^4+'FCFF Build'!$G$14/(1+$A5)^5+('FCFF Build'!$G$14*(1+B$4)/($A5-B$4))/(1+$A5)^5-'DCF Valuation'!$B$19+'DCF Valuation'!$B$20)/'DCF Valuation'!$B$22 -> 1170.8533 | C5: =('FCFF Build'!$C$14/(1+$A5)^1+'FCFF Build'!$D$14/(1+$A5)^2+'FCFF Build'!$E$14/(1+$A5)^3+'FCFF Build'!$F$14/(1+$A5)^4+'FCFF Build'!$G$14/(1+$A5)^5+('FCFF Build'!$G$14*(1+C$4)/($A5-C$4))/(1+$A5)^5-'DCF Valuation'!$B$19+'DCF Valuation'!$B$20)/'DCF Valuation'!$B$22 -> 1254.4262 | D5: =('FCFF Build'!$C$14/(1+$A5)^1+'FCFF Build'!$D$14/(1+$A5)^2+'FCFF Build'!$E$14/(1+$A5)^3+'FCFF Build'!$F$14/(1+$A5)^4+'FCFF Build'!$G$14/(1+$A5)^5+('FCFF Build'!$G$14*(1+D$4)/($A5-D$4))/(1+$A5)^5-'DCF Valuation'!$B$19+'DCF Valuation'!$B$20)/'DCF Valuation'!$B$22 -> 1353.8674 | E5: =('FCFF Build'!$C$14/(1+$A5)^1+'FCFF Build'!$D$14/(1+$A5)^2+'FCFF Build'!$E$14/(1+$A5)^3+'FCFF Build'!$F$14/(1+$A5)^4+'FCFF Build'!$G$14/(1+$A5)^5+('FCFF Build'!$G$14*(1+E$4)/($A5-E$4))/(1+$A5)^5-'DCF Valuation'!$B$19+'DCF Valuation'!$B$20)/'DCF Valuation'!$B$22 -> 1474.1704 | F5: =('FCFF Build'!$C$14/(1+$A5)^1+'FCFF Build'!$D$14/(1+$A5)^2+'FCFF Build'!$E$14/(1+$A5)^3+'FCFF Build'!$F$14/(1+$A5)^4+'FCFF Build'!$G$14/(1+$A5)^5+('FCFF Build'!$G$14*(1+F$4)/($A5-F$4))/(1+$A5)^5-'DCF Valuation'!$B$19+'DCF Valuation'!$B$20)/'DCF Valuation'!$B$22 -> 1622.6694
A6: 0.087 | B6: =('FCFF Build'!$C$14/(1+$A6)^1+'FCFF Build'!$D$14/(1+$A6)^2+'FCFF Build'!$E$14/(1+$A6)^3+'FCFF Build'!$F$14/(1+$A6)^4+'FCFF Build'!$G$14/(1+$A6)^5+('FCFF Build'!$G$14*(1+B$4)/($A6-B$4))/(1+$A6)^5-'DCF Valuation'!$B$19+'DCF Valuation'!$B$20)/'DCF Valuation'!$B$22 -> 1060.201 | C6: =('FCFF Build'!$C$14/(1+$A6)^1+'FCFF Build'!$D$14/(1+$A6)^2+'FCFF Build'!$E$14/(1+$A6)^3+'FCFF Build'!$F$14/(1+$A6)^4+'FCFF Build'!$G$14/(1+$A6)^5+('FCFF Build'!$G$14*(1+C$4)/($A6-C$4))/(1+$A6)^5-'DCF Valuation'!$B$19+'DCF Valuation'!$B$20)/'DCF Valuation'!$B$22 -> 1126.6731 | D6: =('FCFF Build'!$C$14/(1+$A6)^1+'FCFF Build'!$D$14/(1+$A6)^2+'FCFF Build'!$E$14/(1+$A6)^3+'FCFF Build'!$F$14/(1+$A6)^4+'FCFF Build'!$G$14/(1+$A6)^5+('FCFF Build'!$G$14*(1+D$4)/($A6-D$4))/(1+$A6)^5-'DCF Valuation'!$B$19+'DCF Valuation'!$B$20)/'DCF Valuation'!$B$22 -> 1204.3485 | E6: =('FCFF Build'!$C$14/(1+$A6)^1+'FCFF Build'!$D$14/(1+$A6)^2+'FCFF Build'!$E$14/(1+$A6)^3+'FCFF Build'!$F$14/(1+$A6)^4+'FCFF Build'!$G$14/(1+$A6)^5+('FCFF Build'!$G$14*(1+E$4)/($A6-E$4))/(1+$A6)^5-'DCF Valuation'!$B$19+'DCF Valuation'!$B$20)/'DCF Valuation'!$B$22 -> 1296.3199 | F6: =('FCFF Build'!$C$14/(1+$A6)^1+'FCFF Build'!$D$14/(1+$A6)^2+'FCFF Build'!$E$14/(1+$A6)^3+'FCFF Build'!$F$14/(1+$A6)^4+'FCFF Build'!$G$14/(1+$A6)^5+('FCFF Build'!$G$14*(1+F$4)/($A6-F$4))/(1+$A6)^5-'DCF Valuation'!$B$19+'DCF Valuation'!$B$20)/'DCF Valuation'!$B$22 -> 1406.9342
A7: 0.092 | B7: =('FCFF Build'!$C$14/(1+$A7)^1+'FCFF Build'!$D$14/(1+$A7)^2+'FCFF Build'!$E$14/(1+$A7)^3+'FCFF Build'!$F$14/(1+$A7)^4+'FCFF Build'!$G$14/(1+$A7)^5+('FCFF Build'!$G$14*(1+B$4)/($A7-B$4))/(1+$A7)^5-'DCF Valuation'!$B$19+'DCF Valuation'!$B$20)/'DCF Valuation'!$B$22 -> 968.96849 | C7: =('FCFF Build'!$C$14/(1+$A7)^1+'FCFF Build'!$D$14/(1+$A7)^2+'FCFF Build'!$E$14/(1+$A7)^3+'FCFF Build'!$F$14/(1+$A7)^4+'FCFF Build'!$G$14/(1+$A7)^5+('FCFF Build'!$G$14*(1+C$4)/($A7-C$4))/(1+$A7)^5-'DCF Valuation'!$B$19+'DCF Valuation'!$B$20)/'DCF Valuation'!$B$22 -> 1022.9163 | D7: =('FCFF Build'!$C$14/(1+$A7)^1+'FCFF Build'!$D$14/(1+$A7)^2+'FCFF Build'!$E$14/(1+$A7)^3+'FCFF Build'!$F$14/(1+$A7)^4+'FCFF Build'!$G$14/(1+$A7)^5+('FCFF Build'!$G$14*(1+D$4)/($A7-D$4))/(1+$A7)^5-'DCF Valuation'!$B$19+'DCF Valuation'!$B$20)/'DCF Valuation'!$B$22 -> 1085.038 | E7: =('FCFF Build'!$C$14/(1+$A7)^1+'FCFF Build'!$D$14/(1+$A7)^2+'FCFF Build'!$E$14/(1+$A7)^3+'FCFF Build'!$F$14/(1+$A7)^4+'FCFF Build'!$G$14/(1+$A7)^5+('FCFF Build'!$G$14*(1+E$4)/($A7-E$4))/(1+$A7)^5-'DCF Valuation'!$B$19+'DCF Valuation'!$B$20)/'DCF Valuation'!$B$22 -> 1157.3435 | F7: =('FCFF Build'!$C$14/(1+$A7)^1+'FCFF Build'!$D$14/(1+$A7)^2+'FCFF Build'!$E$14/(1+$A7)^3+'FCFF Build'!$F$14/(1+$A7)^4+'FCFF Build'!$G$14/(1+$A7)^5+('FCFF Build'!$G$14*(1+F$4)/($A7-F$4))/(1+$A7)^5-'DCF Valuation'!$B$19+'DCF Valuation'!$B$20)/'DCF Valuation'!$B$22 -> 1242.5608
A8: 0.097 | B8: =('FCFF Build'!$C$14/(1+$A8)^1+'FCFF Build'!$D$14/(1+$A8)^2+'FCFF Build'!$E$14/(1+$A8)^3+'FCFF Build'!$F$14/(1+$A8)^4+'FCFF Build'!$G$14/(1+$A8)^5+('FCFF Build'!$G$14*(1+B$4)/($A8-B$4))/(1+$A8)^5-'DCF Valuation'!$B$19+'DCF Valuation'!$B$20)/'DCF Valuation'!$B$22 -> 892.45732 | C8: =('FCFF Build'!$C$14/(1+$A8)^1+'FCFF Build'!$D$14/(1+$A8)^2+'FCFF Build'!$E$14/(1+$A8)^3+'FCFF Build'!$F$14/(1+$A8)^4+'FCFF Build'!$G$14/(1+$A8)^5+('FCFF Build'!$G$14*(1+C$4)/($A8-C$4))/(1+$A8)^5-'DCF Valuation'!$B$19+'DCF Valuation'!$B$20)/'DCF Valuation'!$B$22 -> 936.97623 | D8: =('FCFF Build'!$C$14/(1+$A8)^1+'FCFF Build'!$D$14/(1+$A8)^2+'FCFF Build'!$E$14/(1+$A8)^3+'FCFF Build'!$F$14/(1+$A8)^4+'FCFF Build'!$G$14/(1+$A8)^5+('FCFF Build'!$G$14*(1+D$4)/($A8-D$4))/(1+$A8)^5-'DCF Valuation'!$B$19+'DCF Valuation'!$B$20)/'DCF Valuation'!$B$22 -> 987.62159 | E8: =('FCFF Build'!$C$14/(1+$A8)^1+'FCFF Build'!$D$14/(1+$A8)^2+'FCFF Build'!$E$14/(1+$A8)^3+'FCFF Build'!$F$14/(1+$A8)^4+'FCFF Build'!$G$14/(1+$A8)^5+('FCFF Build'!$G$14*(1+E$4)/($A8-E$4))/(1+$A8)^5-'DCF Valuation'!$B$19+'DCF Valuation'!$B$20)/'DCF Valuation'!$B$22 -> 1045.7515 | F8: =('FCFF Build'!$C$14/(1+$A8)^1+'FCFF Build'!$D$14/(1+$A8)^2+'FCFF Build'!$E$14/(1+$A8)^3+'FCFF Build'!$F$14/(1+$A8)^4+'FCFF Build'!$G$14/(1+$A8)^5+('FCFF Build'!$G$14*(1+F$4)/($A8-F$4))/(1+$A8)^5-'DCF Valuation'!$B$19+'DCF Valuation'!$B$20)/'DCF Valuation'!$B$22 -> 1113.1574
A9: 0.102 | B9: =('FCFF Build'!$C$14/(1+$A9)^1+'FCFF Build'!$D$14/(1+$A9)^2+'FCFF Build'!$E$14/(1+$A9)^3+'FCFF Build'!$F$14/(1+$A9)^4+'FCFF Build'!$G$14/(1+$A9)^5+('FCFF Build'!$G$14*(1+B$4)/($A9-B$4))/(1+$A9)^5-'DCF Valuation'!$B$19+'DCF Valuation'!$B$20)/'DCF Valuation'!$B$22 -> 827.3715 | C9: =('FCFF Build'!$C$14/(1+$A9)^1+'FCFF Build'!$D$14/(1+$A9)^2+'FCFF Build'!$E$14/(1+$A9)^3+'FCFF Build'!$F$14/(1+$A9)^4+'FCFF Build'!$G$14/(1+$A9)^5+('FCFF Build'!$G$14*(1+C$4)/($A9-C$4))/(1+$A9)^5-'DCF Valuation'!$B$19+'DCF Valuation'!$B$20)/'DCF Valuation'!$B$22 -> 864.62756 | D9: =('FCFF Build'!$C$14/(1+$A9)^1+'FCFF Build'!$D$14/(1+$A9)^2+'FCFF Build'!$E$14/(1+$A9)^3+'FCFF Build'!$F$14/(1+$A9)^4+'FCFF Build'!$G$14/(1+$A9)^5+('FCFF Build'!$G$14*(1+D$4)/($A9-D$4))/(1+$A9)^5-'DCF Valuation'!$B$19+'DCF Valuation'!$B$20)/'DCF Valuation'!$B$22 -> 906.57977 | E9: =('FCFF Build'!$C$14/(1+$A9)^1+'FCFF Build'!$D$14/(1+$A9)^2+'FCFF Build'!$E$14/(1+$A9)^3+'FCFF Build'!$F$14/(1+$A9)^4+'FCFF Build'!$G$14/(1+$A9)^5+('FCFF Build'!$G$14*(1+E$4)/($A9-E$4))/(1+$A9)^5-'DCF Valuation'!$B$19+'DCF Valuation'!$B$20)/'DCF Valuation'!$B$22 -> 954.17576 | F9: =('FCFF Build'!$C$14/(1+$A9)^1+'FCFF Build'!$D$14/(1+$A9)^2+'FCFF Build'!$E$14/(1+$A9)^3+'FCFF Build'!$F$14/(1+$A9)^4+'FCFF Build'!$G$14/(1+$A9)^5+('FCFF Build'!$G$14*(1+F$4)/($A9-F$4))/(1+$A9)^5-'DCF Valuation'!$B$19+'DCF Valuation'!$B$20)/'DCF Valuation'!$B$22 -> 1008.6366
A11: Base case (center cell, bold border) matches DCF Valuation tab per-share value.
A12: Current market price: Rs 2,170 (18-Jul-2026).

Sheet Comps Cross-Check
A1: HUL - Relative Valuation Cross-Check (EV/EBITDA & P/E vs FMCG Peers)
A2: Purpose: sanity-check the DCF output against what public FMCG peer multiples imply for HUL.
A4: Company | B4: P/E (x, TTM) | C4: EV/EBITDA (x, TTM) | D4: Used in peer median? | F4: Source
A5: Hindustan Unilever (self) | B5: 48 | C5: 34 | D5: Reference only | F5: Median of multiple live sources (Screener/MarketsMojo/Tijori/Yahoo), Jul-2026 - shown for reference, excluded from peer set
A6: Nestle India | B6: 77.7 | C6: 51 | D6: No - premium outlier | F6: ValueResearchOnline (23-Apr-2026); valueinvesting.io (1-Jan-2026). Trades at ~2x sector median; excluded as non-representative
A7: Colgate-Palmolive India | B7: 41.6 | C7: 28 | D7: Yes | F7: Multiples.vc (7-Jun-2026); MarketScreener (2026)
A8: Dabur India | B8: 33.8 | C8: 33 | D8: Yes | F8: companiesmarketcap.com; valueinvesting.io / investing.com (Feb-2026)
A9: ITC Ltd | B9: 17.1 | C9: 12.9 | D9: No - diversified conglomerate | F9: stockanalysis.com; ValueResearchOnline (Jul-2026). Cigarettes-led earnings mix, not FMCG pure-play
A11: Peer set for median = Colgate-Palmolive India + Dabur India only.
A12: Nestle India excluded (trades at a structural premium unrelated to HUL's growth/margin profile).
A13: ITC excluded (cigarettes drive ~80% of profit; not a comparable business or risk profile).
A15: Peer Median P/E (x) | B15: =MEDIAN(B7,B8) -> 37.7
A16: Peer Median EV/EBITDA (x) | B16: =MEDIAN(C7,C8) -> 30.5
A18: Implied HUL Valuation from Peer Multiples
A19: HUL FY26A EBITDA (EBIT + D&A, Rs Cr) | B19: =Historicals!D6+Historicals!D9 -> 16372
A20: Implied EV (Peer Median EV/EBITDA x FY26A EBITDA, Rs Cr) | B20: =B16*B19 -> 499346
A21: (-) Total Debt (Rs Cr) | B21: =-Assumptions!B11 -> -1478
A22: (+) Cash & Investments (Rs Cr) | B22: =Historicals!D18 -> 4359
A23: Implied Equity Value (Rs Cr) | B23: =B20+B21+B22 -> 502227
A24: Shares Outstanding (Cr) | B24: =Historicals!D19 -> 235
A25: Implied Value per Share - EV/EBITDA method (Rs) | B25: =B23/B24 -> 2137.1362
A27: HUL FY26A Normalized PAT (EBIT x (1-Normalized Tax), Rs Cr) | B27: =Historicals!D6*(1-Assumptions!B9) -> 11204.055
A28: Note: excludes FY26 one-off Other Income & related tax anomaly, for consistency with DCF base
A29: Implied Value per Share - P/E method (Rs) | B29: =(B27/B24)*B15 -> 1797.4165
A31: Comparison
A32: DCF Value per Share (Rs) | B32: ='DCF Valuation'!B23 -> 1087.7497
A33: Peer EV/EBITDA-Implied Value per Share (Rs) | B33: =B25 -> 2137.1362
A34: Current Market Price (Rs) | B34: ='DCF Valuation'!B24 -> 2170
A36: Takeaway: the DCF and peer-multiple cross-check diverge because a WACC/terminal-growth DCF is conservative relative to how the market prices HUL's brand moat and cash-flow stability, while peer trading multiples capture that premium directly.
